system_diag_mcp/__init__.py
system_diag_mcp/server.py
system_diag_mcp-0.1.0.dist-info/METADATA
system_diag_mcp-0.1.0.dist-info/WHEEL
system_diag_mcp-0.1.0.dist-info/entry_points.txt
system_diag_mcp-0.1.0.dist-info/licenses/LICENSE
system_diag_mcp-0.1.0.dist-info/RECORD
