Metadata-Version: 2.4
Name: system-diag-mcp
Version: 0.1.0
Summary: MCP server for Ubuntu system diagnostics and monitoring
Author-email: System Diagnostics Team <admin@example.com>
License: MIT
License-File: LICENSE
Requires-Python: >=3.8
Requires-Dist: mcp
Requires-Dist: psutil>=5.9.0
Requires-Dist: requests>=2.28.0
Provides-Extra: dev
Requires-Dist: black>=23.0.0; extra == 'dev'
Requires-Dist: pytest-asyncio>=0.21.0; extra == 'dev'
Requires-Dist: pytest>=7.0.0; extra == 'dev'
Requires-Dist: ruff>=0.1.0; extra == 'dev'
